setup.py
ccsdk/__init__.py
ccsdk/help.py
ccsdk.egg-info/PKG-INFO
ccsdk.egg-info/SOURCES.txt
ccsdk.egg-info/dependency_links.txt
ccsdk.egg-info/top_level.txt