Metadata-Version: 1.0
Name: ccsdk
Version: 0.0.2
Summary: cc sdk
Home-page: http://jmhuang.me
Author: jmhuang
Author-email: jmhuang@corp.netease.com
License: MIT License
Keywords: pip,datacanvas,eds,jmhuang
Platform: any
